dpivsoft/Cl_DPIV.py
dpivsoft/Classes.py
dpivsoft/DPIV.py
dpivsoft/Postprocessing.py
dpivsoft/SyIm.py
dpivsoft/__init__.py
dpivsoft/meshTools.py
dpivsoft/stereo_DPIV.py
dpivsoft/Examples/Performance.py
dpivsoft/Examples/Performance_parameters.yaml
dpivsoft/Examples/forces_tutorial.py
dpivsoft/Examples/mesh_tutorial.py
dpivsoft/Examples/performance.py
dpivsoft/Examples/performance_parameters.yaml
dpivsoft/Examples/simple_tutorial.py
dpivsoft/Examples/simple_tutorial_parameters.yaml
dpivsoft/Examples/stereo_tutorial.py
dpivsoft/Examples/stereo_tutorial_parameters.yaml
dpivsoft/Examples/CFD/Mixing_Flow.npy
dpivsoft/GPU_Kernels/Jacobian.cl
dpivsoft/GPU_Kernels/Normalize_Img.cl
dpivsoft/GPU_Kernels/Slice.cl
dpivsoft/GPU_Kernels/SubMean.cl
dpivsoft/GPU_Kernels/Weighting.cl
dpivsoft/GPU_Kernels/box_blur.cl
dpivsoft/GPU_Kernels/deform_image.cl
dpivsoft/GPU_Kernels/directCorrelation.cl
dpivsoft/GPU_Kernels/find_peak.cl
dpivsoft/GPU_Kernels/find_peak_direct.cl
dpivsoft/GPU_Kernels/gaussian_filter.cl
dpivsoft/GPU_Kernels/ini_index.cl
dpivsoft/GPU_Kernels/interpolation.cl
dpivsoft/GPU_Kernels/median_filter.cl
dpivsoft/GPU_Kernels/multiply_them.cl
dpivsoft-0.4.0.dist-info/LICENSE.txt
dpivsoft-0.4.0.dist-info/METADATA
dpivsoft-0.4.0.dist-info/WHEEL
dpivsoft-0.4.0.dist-info/top_level.txt
dpivsoft-0.4.0.dist-info/RECORD
