Metadata-Version: 2.1
Name: dpivsoft
Version: 0.4.0
Home-page: https://gitlab.com/jacabello/dpivsoft_python
Author: Jorge Aguilar-Cabello
Classifier: Programming Language :: Python :: 3.7
Classifier: Programming Language :: Python :: 3.8
Classifier: Programming Language :: Python :: 3.9
Classifier: Programming Language :: Python :: 3.10
Classifier: Intended Audience :: Science/Research
Classifier: License :: OSI Approved :: GNU General Public License v3 (GPLv3)
Classifier: Natural Language :: English
Requires-Python: >=3.7
License-File: LICENSE.txt
Requires-Dist: Pillow (>=9)
Requires-Dist: PyYAML (>=5.4)
Requires-Dist: Shapely (>=1.7)
Requires-Dist: gmsh (==4.13.1)
Requires-Dist: importlib-resources (>=5)
Requires-Dist: matplotlib (>=3)
Requires-Dist: meshio (==5.3.5)
Requires-Dist: numpy (<1.24.0,>=1.3)
Requires-Dist: opencv-python (==4.8.0.74)
Requires-Dist: pyopencl (>=2021)
Requires-Dist: reikna (>=0.7.6)
Requires-Dist: scikit-fem (==10.0.2)
Requires-Dist: scikit-image (>=0.20)
Requires-Dist: scikit-learn
Requires-Dist: scipy (==1.11.1)
Provides-Extra: dev
Requires-Dist: pytest (>=3.7) ; extra == 'dev'
